decision_section/__init__.py
decision_section/__main__.py
decision_section/blockquotes.py
decision_section/combiner.py
decision_section/wrapper.py
decision_section-0.0.1.dist-info/WHEEL
decision_section-0.0.1.dist-info/METADATA
decision_section-0.0.1.dist-info/RECORD
